packel/__init__.py
packel/packet.py
packel/protocol.py
packel/types.py
packel-1.0.1.dist-info/METADATA
packel-1.0.1.dist-info/WHEEL
packel-1.0.1.dist-info/top_level.txt
packel-1.0.1.dist-info/RECORD
